sbkube/__init__.py
sbkube/cli.py
sbkube/exceptions.py
sbkube/commands/__init__.py
sbkube/commands/apply.py
sbkube/commands/assistant.py
sbkube/commands/build.py
sbkube/commands/config.py
sbkube/commands/delete.py
sbkube/commands/deploy.py
sbkube/commands/doctor.py
sbkube/commands/fix.py
sbkube/commands/history.py
sbkube/commands/init.py
sbkube/commands/prepare.py
sbkube/commands/profiles.py
sbkube/commands/state.py
sbkube/commands/template.py
sbkube/commands/upgrade.py
sbkube/commands/validate.py
sbkube/commands/version.py
sbkube/diagnostics/__init__.py
sbkube/diagnostics/kubernetes_checks.py
sbkube/fixes/__init__.py
sbkube/fixes/namespace_fixes.py
sbkube/models/__init__.py
sbkube/models/base_model.py
sbkube/models/config_manager.py
sbkube/models/config_model.py
sbkube/models/deployment_state.py
sbkube/models/execution_state.py
sbkube/models/sources_model.py
sbkube/models/validators.py
sbkube/state/__init__.py
sbkube/state/database.py
sbkube/state/rollback.py
sbkube/state/tracker.py
sbkube/templates/basic/config.yaml.j2
sbkube/templates/basic/sources.yaml.j2
sbkube/templates/basic/values/app-values.yaml.j2
sbkube/utils/auto_fix_system.py
sbkube/utils/base_command.py
sbkube/utils/cli_check.py
sbkube/utils/cmd_executor.py
sbkube/utils/common.py
sbkube/utils/context_aware_suggestions.py
sbkube/utils/diagnostic_system.py
sbkube/utils/error_suggestions.py
sbkube/utils/execution_tracker.py
sbkube/utils/file_loader.py
sbkube/utils/helm_util.py
sbkube/utils/interactive_assistant.py
sbkube/utils/kubeconfig_info.py
sbkube/utils/logger.py
sbkube/utils/pattern_analyzer.py
sbkube/utils/profile_loader.py
sbkube/utils/profile_manager.py
sbkube/utils/progress_manager.py
sbkube/utils/retry.py
sbkube/utils/validation_report.py
sbkube/utils/validation_system.py
sbkube/validators/__init__.py
sbkube/validators/basic_validators.py
sbkube/validators/configuration_validators.py
sbkube/validators/dependency_validators.py
sbkube/validators/environment_validators.py
sbkube-0.4.7.dist-info/METADATA
sbkube-0.4.7.dist-info/WHEEL
sbkube-0.4.7.dist-info/entry_points.txt
sbkube-0.4.7.dist-info/licenses/LICENSE
sbkube-0.4.7.dist-info/RECORD
