Metadata-Version: 2.4
Name: sbkube
Version: 0.4.7
Summary: k3s용 헬름+yaml+git 배포 자동화 CLI 도구
Author-email: archmagece <archmagece@users.noreply.github.com>
License-Expression: MIT
License-File: LICENSE
Requires-Python: >=3.12
Requires-Dist: click>=8.1
Requires-Dist: gitpython
Requires-Dist: jinja2
Requires-Dist: jsonschema>=4.23.0
Requires-Dist: kubernetes>=28.1.0
Requires-Dist: pydantic>=2.7.1
Requires-Dist: pyyaml
Requires-Dist: requests>=2.31.0
Requires-Dist: rich
Requires-Dist: sqlalchemy>=2.0.0
Requires-Dist: toml>=0.10.2
